enigma_deena_andre_lib/__init__.py
enigma_deena_andre_lib/enigma_deena_andre.py
enigma_deena_andre-0.0.17.dist-info/METADATA
enigma_deena_andre-0.0.17.dist-info/WHEEL
enigma_deena_andre-0.0.17.dist-info/top_level.txt
enigma_deena_andre-0.0.17.dist-info/RECORD
