Metadata-Version: 2.1
Name: enigma-deena-andre
Version: 0.0.17
Summary: Biblioteca da APS 2 para disciplina de algebra linear
Author: Deena & Andre
Requires-Python: >=3.10
Requires-Dist: numpy ==1.26.4
Provides-Extra: dev
Requires-Dist: twine >=4.0.2 ; extra == 'dev'
